MANIFEST.in
README.rst
setup.py
alfredo/PyGtalkRobot.py
alfredo/__init__.py
alfredo.egg-info/PKG-INFO
alfredo.egg-info/SOURCES.txt
alfredo.egg-info/dependency_links.txt
alfredo.egg-info/requires.txt
alfredo.egg-info/top_level.txt
alfredo/commands/__init__.py
alfredo/commands/base.py
alfredo/commands/help.py
alfredo/commands/invert.py
alfredo/commands/megaupload.py
alfredo/commands/ramal.py
alfredo/commands/urbandictionary.py
script/alfredo
script/ud