Metadata-Version: 1.1
Name: alfredo
Version: 0.2
Summary: Alfredo is a gtalk bot born so serve you.
Home-page: https://github.com/daltonmatos/alfredo
Author: Dalton Barreto
Author-email: daltonmatos@gmail.com
License: 3-BSD
Platform: UNKNOWN
Classifier: License :: OSI Approved :: BSD License
Classifier: Operating System :: OS Independent
Classifier: Programming Language :: Python
Classifier: Topic :: Software Development :: Libraries :: Application Frameworks
